Flask_json_schema-0.0.5.dist-info/METADATA
Flask_json_schema-0.0.5.dist-info/RECORD
Flask_json_schema-0.0.5.dist-info/WHEEL
Flask_json_schema-0.0.5.dist-info/top_level.txt
flask_json_schema/__init__.py
