Metadata-Version: 2.1
Name: Flask-json-schema
Version: 0.0.5
Summary: Flask extension to validate JSON requests
Home-page: https://github.com/sanjeevan/flask-json-schema
Author: Sanjeevan Ambalavanar
Author-email: sanjeevan@pureparadox.com
License: MIT
Platform: UNKNOWN
Classifier: License :: OSI Approved :: MIT License
Classifier: Operating System :: OS Independent
